aico/__init__.py
aico/backup.py
aico/bootstrap.py
aico/chat.py
aico/console_ui.py
aico/const.py
aico/core.py
aico/diff.py
aico/file_processing.py
aico/gen.py
aico/git.py
aico/main.py
aico/utils.py
seniorai-0.1.0.dist-info/entry_points.txt
seniorai-0.1.0.dist-info/METADATA
seniorai-0.1.0.dist-info/WHEEL
seniorai-0.1.0.dist-info/RECORD
