Metadata-Version: 2.1
Name: seniorai
Version: 0.1.0
Summary: AI coding assistant
Author: Nayjest
Author-email: mail@vitaliy.in
Requires-Python: >=3.11,<4.0
Classifier: Programming Language :: Python :: 3
Classifier: Programming Language :: Python :: 3.11
Classifier: Programming Language :: Python :: 3.12
